zefir_analytics/__init__.py
zefir_analytics/zefir_engine.py
zefir_analytics/_engine/__init__.py
zefir_analytics/_engine/constants.py
zefir_analytics/_engine/data_loader.py
zefir_analytics/_engine/data_queries/__init__.py
zefir_analytics/_engine/data_queries/aggregated_consumer_parameters_over_years.py
zefir_analytics/_engine/data_queries/lbs_parameters_over_years.py
zefir_analytics/_engine/data_queries/line_parameters_over_years.py
zefir_analytics/_engine/data_queries/source_parameters_over_years.py
zefir_analytics/_engine/data_queries/utils.py
zefir_analytics-0.4.30.dist-info/LICENSE
zefir_analytics-0.4.30.dist-info/LICENSE.txt
zefir_analytics-0.4.30.dist-info/METADATA
zefir_analytics-0.4.30.dist-info/WHEEL
zefir_analytics-0.4.30.dist-info/top_level.txt
zefir_analytics-0.4.30.dist-info/RECORD
