Metadata-Version: 2.1
Name: zefir-analytics
Version: 0.4.30
Author-email: Narodowe Centrum Badań Jądrowych <office@idea.edu.pl>
License: GNU AFFERO GENERAL PUBLIC LICENSE
Classifier: Environment :: Console
Classifier: Intended Audience :: Science/Research
Classifier: License :: OSI Approved :: GNU Affero General Public License v3 or later (AGPLv3+)
Classifier: Natural Language :: English
Classifier: Operating System :: OS Independent
Classifier: Programming Language :: Python :: 3.11
Classifier: Topic :: Scientific/Engineering
License-File: LICENSE
License-File: LICENSE.txt
Requires-Dist: numpy~=1.24.2
Requires-Dist: pandas==2.0.1
Requires-Dist: pyzefir<0.6.0,>=0.5.0
Provides-Extra: dev
Requires-Dist: pre-commit; extra == "dev"
Requires-Dist: pytest==7.4.4; extra == "dev"
Requires-Dist: flake8; extra == "dev"
Requires-Dist: black==24.2.0; extra == "dev"
Requires-Dist: pytest-cov~=4.1.0; extra == "dev"
Requires-Dist: pytest-mock~=3.11.1; extra == "dev"
Requires-Dist: pytest-lazy-fixture~=0.6.3; extra == "dev"
Requires-Dist: pytest-xdist~=3.5.0; extra == "dev"
Requires-Dist: pylama[mccabe,mypy,pycodestyle,pyflakes,radon,toml]; extra == "dev"
Requires-Dist: tox; extra == "dev"
